labdiscoveryengine/__init__.py
labdiscoveryengine/cli.py
labdiscoveryengine/data.py
labdiscoveryengine/exc.py
labdiscoveryengine/keys.py
labdiscoveryengine/configuration/__init__.py
labdiscoveryengine/configuration/exc.py
labdiscoveryengine/configuration/storage.py
labdiscoveryengine/configuration/variables.py
labdiscoveryengine-0.0.1.dist-info/LICENSE
labdiscoveryengine-0.0.1.dist-info/METADATA
labdiscoveryengine-0.0.1.dist-info/WHEEL
labdiscoveryengine-0.0.1.dist-info/entry_points.txt
labdiscoveryengine-0.0.1.dist-info/top_level.txt
labdiscoveryengine-0.0.1.dist-info/RECORD
