Metadata-Version: 2.1
Name: labdiscoveryengine
Version: 0.0.1
Summary: Remote Laboratory Management System for creating laboratories (replacement of WebLab-Deusto)
Home-page: https://developers.labsland.com/labdiscoveryengine/
Author: LabsLand
Author-email: dev@labsland.com
License: GNU AGPL v3
Project-URL: Documentation, https://developers.labsland.com/labdiscoveryengine/en/stable/
Project-URL: Code, https://github.com/labsland/labdiscoveryengine
Project-URL: Issue tracker, https://github.com/labsland/labdiscoveryengine/issues
Platform: UNKNOWN
Classifier: Development Status :: 1 - Planning
Classifier: Environment :: Web Environment
Classifier: Intended Audience :: Developers
Classifier: License :: OSI Approved :: GNU Affero General Public License v3
Classifier: Operating System :: OS Independent
Classifier: Programming Language :: Python
Classifier: Programming Language :: Python :: 3
Classifier: Programming Language :: Python :: 3.10
Classifier: Topic :: Education
Classifier: Topic :: Internet :: WWW/HTTP
License-File: LICENSE
Requires-Dist: Flask (==2.3.3)
Requires-Dist: Jinja2 (==3.1.2)
Requires-Dist: MarkupSafe (==2.1.3)
Requires-Dist: PyYAML (==6.0.1)
Requires-Dist: Werkzeug (==2.3.7)
Requires-Dist: blinker (==1.6.2)
Requires-Dist: click (==8.1.7)
Requires-Dist: itsdangerous (==2.1.2)
